generic_scaffold
